{"name": "Skilled Red Magician", "img": "https://ygohub.com/card_images/e7839a77-c943-4cbf-9b05-47ce036caf55.jpg", "text": "Each time a Spell Card is activated, place 1 Spell Counter on this card when that Spell Card resolves (max. 3). You can Tribute this card with 3 Spell Counters on it; Special Summon 1 \"Archfiend\" monster from your hand, Deck, or Graveyard. You can banish this card from your Graveyard, then target 1 card you control that you can place a Spell Counter on; place 1 Spell Counter on it.", "cardType": "Monster", "number": "65338781", "isMonster": true, "isSpell": false, "isTrap": false, "property": null, "monsterTypes": ["Effect"], "species": "Spellcaster", "ATK": "1600", "DEF": "1600", "level": "4", "attribute": "DARK", "isExtraDeck": false, "hasMaterials": false, "materials": null, "sources": ["Wonders of the Sky"], "traderCost": null, "rarity": "SR", "limit": 3}