{"name": "Exterio's Fang", "img": "https://ygohub.com/card_images/0d0e26ae-8b0b-48b5-a4d0-e732d86f4a97.jpg", "text": "Activate only if you control a face-up \"Naturia\" monster and have at least 1 card in your hand. Negate the activation of an opponent's Spell/Trap Card and destroy it. Then, send 1 card from your hand to the Graveyard.", "cardType": "Trap", "number": "68456353", "isMonster": false, "isSpell": false, "isTrap": true, "property": "Counter", "monsterTypes": [], "species": null, "ATK": null, "DEF": null, "level": null, "attribute": null, "isExtraDeck": false, "hasMaterials": false, "materials": null, "sources": ["Dawn of Destiny"], "traderCost": null, "rarity": "N", "limit": 3}