{"name": "Trifortressops", "img": "https://ygohub.com/card_images/58f9504a96ffd.jpg", "text": "During either player's turn, if your opponent Summoned 3 or more monsters this turn: You can Special Summon this card from your hand. If Summoned this way, it is unaffected by other cards' effects, but loses 500 DEF during each player's Standby Phase.", "cardType": "Monster", "number": "12275533", "isMonster": true, "isSpell": false, "isTrap": false, "property": null, "monsterTypes": ["Effect"], "species": "Machine", "ATK": "1600", "DEF": "2800", "level": "6", "attribute": "DARK", "isExtraDeck": false, "hasMaterials": false, "materials": null, "sources": ["Galactic Origin"], "traderCost": null, "rarity": "UR", "limit": 3}