{"name": "Reverse Trap", "img": "https://ygohub.com/card_images/88c81037-cdc2-4da1-b752-3b959bab6875.jpg", "text": "Until the End Phase, all effects that add or subtract ATK or DEF are reversed. (Additions now subtract, and subtractions now add, instead. Multiplications and divisions, including halving/doubling, are not affected.)", "cardType": "Trap", "number": "77622396", "isMonster": false, "isSpell": false, "isTrap": true, "property": "Normal", "monsterTypes": [], "species": null, "ATK": null, "DEF": null, "level": null, "attribute": null, "isExtraDeck": false, "hasMaterials": false, "materials": null, "sources": ["Ranked Ticket Rewards"], "traderCost": null, "rarity": "SR", "limit": 3}