{"name": "Machine King - 3000 B.C.", "img": "https://ygohub.com/card_images/58f94fad714ad.jpg", "text": "Special Summon this card as an Effect Monster (Machine-Type/EARTH/Level 4/ATK 1000/DEF 1000). (This card is also still a Trap Card.) You cannot Normal or Special Summon other monsters the turn you activate this card. Once per turn, during your Main Phase: You can Tribute 1 Machine-Type monster; this card gains ATK equal to the ATK the Tributed monster had on the field, until the end of this turn.", "cardType": "Trap", "number": "70406920", "isMonster": false, "isSpell": false, "isTrap": true, "property": "Continuous", "monsterTypes": [], "species": null, "ATK": null, "DEF": null, "level": null, "attribute": null, "isExtraDeck": false, "hasMaterials": false, "materials": null, "sources": ["Chaotic Compliance"], "traderCost": null, "rarity": "N", "limit": 3}