{"name": "Telekinetic Shocker", "img": "https://ygohub.com/card_images/81456393-4a1f-44ca-a77f-dd21f8688d9d.jpg", "text": "If a Psychic-Type monster(s) on the field would be destroyed, you can pay 500 LP and destroy this card instead.", "cardType": "Monster", "number": "84847656", "isMonster": true, "isSpell": false, "isTrap": false, "property": null, "monsterTypes": ["Effect"], "species": "Psychic", "ATK": "1700", "DEF": "700", "level": "4", "attribute": "EARTH", "isExtraDeck": false, "hasMaterials": false, "materials": null, "sources": ["Chaotic Compliance"], "traderCost": null, "rarity": "R", "limit": 3}