{"name": "Leotaur", "img": "https://ygohub.com/card_images/9f19b23c-f0f4-4f0e-b03b-e6a5ee577ed8.jpg", "text": "If this card battles a non-Normal Monster, this card gains 500 ATK during the Damage Step only.", "cardType": "Monster", "number": "98225108", "isMonster": true, "isSpell": false, "isTrap": false, "property": null, "monsterTypes": ["Effect"], "species": "Beast-Warrior", "ATK": "1500", "DEF": "1600", "level": "4", "attribute": "EARTH", "isExtraDeck": false, "hasMaterials": false, "materials": null, "sources": ["Neo Impact"], "traderCost": null, "rarity": "SR", "limit": 3}