{"name": "Slate Warrior", "img": "https://ygohub.com/card_images/0b4a944c-2434-4ccc-8ad3-3f3d987fdd3c.jpg", "text": "FLIP: This card gains 500 ATK and DEF.If this card is destroyed by battle: The monster that destroyed it loses 500 ATK and DEF.", "cardType": "Monster", "number": "78636495", "isMonster": true, "isSpell": false, "isTrap": false, "property": null, "monsterTypes": ["Flip", "Effect"], "species": "Fiend", "ATK": "1900", "DEF": "400", "level": "4", "attribute": "WIND", "isExtraDeck": false, "hasMaterials": false, "materials": null, "sources": ["Abyss Encounters"], "traderCost": null, "rarity": "UR", "limit": 3}