{"name": "Mystic Swordsman LV2", "img": "https://ygohub.com/card_images/b7ade79f-7fbb-433a-986f-79c6b0c7414f.jpg", "text": "At the start of the Damage Step, if this card attacked a face-down Defense Position monster: Destroy that monster. During the End Phase, if this card destroyed a monster by battle this turn: You can send this face-up card to the Graveyard; Special Summon 1 \"Mystic Swordsman LV4\" from your hand or Deck.", "cardType": "Monster", "number": "47507260", "isMonster": true, "isSpell": false, "isTrap": false, "property": null, "monsterTypes": ["Effect"], "species": "Warrior", "ATK": "900", "DEF": "0", "level": "2", "attribute": "EARTH", "isExtraDeck": false, "hasMaterials": false, "materials": null, "sources": ["Servant of Kings"], "traderCost": null, "rarity": "R", "limit": 3}