{"name": "Chain Ignition", "img": "https://ygohub.com/card_images/e5c444cc-a9b0-4aee-badb-42bf13888135.jpg", "text": "Once per turn, if a monster(s) your opponent controls is destroyed by your opponent's card effect (except during the Damage Step): You can target 1 card on the field; destroy that target.", "cardType": "Trap", "number": "85893201", "isMonster": false, "isSpell": false, "isTrap": true, "property": "Continuous", "monsterTypes": [], "species": null, "ATK": null, "DEF": null, "level": null, "attribute": null, "isExtraDeck": false, "hasMaterials": false, "materials": null, "sources": ["Electric Overload"], "traderCost": null, "rarity": "N", "limit": 3}